random_int/Spider.py
random_int/__init__.py
random_int/random_int_recognition.py
random_int-0.0.5.dist-info/METADATA
random_int-0.0.5.dist-info/WHEEL
random_int-0.0.5.dist-info/top_level.txt
random_int-0.0.5.dist-info/RECORD
