Metadata-Version: 2.1
Name: random-int
Version: 0.0.5
Summary: Get a random number
Author: Rtt.01_-v
Author-email: 2835836810@qq.com
